CHANGELOG.md
CREDITS.md
EULA
LICENSE
LICENSE.rst
LICENSE.txt
MANIFEST.in
README.md
README.rst
VERSION
requirements.txt
setup.cfg
setup.py
src/termsteel/__init__.py
src/termsteel/__main__.py
src/termsteel/app.py
src/termsteel/config.json
src/termsteel.egg-info/PKG-INFO
src/termsteel.egg-info/SOURCES.txt
src/termsteel.egg-info/dependency_links.txt
src/termsteel.egg-info/entry_points.txt
src/termsteel.egg-info/not-zip-safe
src/termsteel.egg-info/requires.txt
src/termsteel.egg-info/top_level.txt
src/termsteel/static/assets/banner.png
src/termsteel/static/assets/grid.svg
src/termsteel/static/assets/logo.png
src/termsteel/static/assets/logo.svg
src/termsteel/static/assets/termsteel_ad.mp4
src/termsteel/static/assets/banner/1.png
src/termsteel/static/assets/banner/2.png
src/termsteel/static/assets/banner/3.png
src/termsteel/static/css/fonts.css
src/termsteel/static/css/static.css
src/termsteel/static/css/tailwind.css
src/termsteel/static/css/xterm.min.css
src/termsteel/static/fonts/poppins-v19-latin-ext_latin_devanagari-100.eot
src/termsteel/static/fonts/poppins-v19-latin-ext_latin_devanagari-100.svg
src/termsteel/static/fonts/poppins-v19-latin-ext_latin_devanagari-100.ttf
src/termsteel/static/fonts/poppins-v19-latin-ext_latin_devanagari-100.woff
src/termsteel/static/fonts/poppins-v19-latin-ext_latin_devanagari-100.woff2
src/termsteel/static/fonts/poppins-v19-latin-ext_latin_devanagari-100italic.eot
src/termsteel/static/fonts/poppins-v19-latin-ext_latin_devanagari-100italic.svg
src/termsteel/static/fonts/poppins-v19-latin-ext_latin_devanagari-100italic.ttf
src/termsteel/static/fonts/poppins-v19-latin-ext_latin_devanagari-100italic.woff
src/termsteel/static/fonts/poppins-v19-latin-ext_latin_devanagari-100italic.woff2
src/termsteel/static/fonts/poppins-v19-latin-ext_latin_devanagari-200.eot
src/termsteel/static/fonts/poppins-v19-latin-ext_latin_devanagari-200.svg
src/termsteel/static/fonts/poppins-v19-latin-ext_latin_devanagari-200.ttf
src/termsteel/static/fonts/poppins-v19-latin-ext_latin_devanagari-200.woff
src/termsteel/static/fonts/poppins-v19-latin-ext_latin_devanagari-200.woff2
src/termsteel/static/fonts/poppins-v19-latin-ext_latin_devanagari-200italic.eot
