Metadata-Version: 2.1
Name: termsteel
Version: 0.0.1.post0
Summary: Termsteel is a versatile and sleek web terminal built in python and accessible from a web browser to interact without complexity with the terminal on your machine inspired on Pyxtermjs.
Home-page: https://github.com/afi-dev/Termsteel
Author: Afi
Author-email: aconique@gmail.com
Project-URL: Bug Reports, https://github.com/afi-dev/Termsteel/issues/new?assignees=&labels=&template=bug_report.md&title=
Project-URL: Feature request, https://github.com/afi-dev/Termsteel/issues/new?assignees=&labels=&template=feature_request.md&title=
Project-URL: Ko-fi, https://ko-fi.com/afidev
Project-URL: Buy me a coffee, https://www.buymeacoffee.com/afidev
Project-URL: Documentation, https://github.com/afi-dev/Termsteel/wiki
Project-URL: Source, https://github.com/afi-dev/Termsteel
Project-URL: Changelog, https://github.com/afi-dev/Termsteel/blob/main/CHANGELOG.md
Keywords: terminal terminal-emulators console browser pty theme termsteel xtermjs flask jwt argon2 alpinejs tailwindcss
Classifier: Operating System :: OS Independent
Classifier: License :: OSI Approved :: MIT License
Classifier: Development Status :: 5 - Production/Stable
Classifier: Intended Audience :: End Users/Desktop
Classifier: Topic :: Desktop Environment
Classifier: Environment :: Web Environment
Classifier: Framework :: Flask
Classifier: Natural Language :: French
Classifier: Natural Language :: German
Classifier: Natural Language :: Spanish
Classifier: Natural Language :: English
Classifier: Programming Language :: JavaScript
Classifier: Programming Language :: Python :: 3
Classifier: Programming Language :: Python :: 3.6
Classifier: Programming Language :: Python :: 3.7
Classifier: Programming Language :: Python :: 3.8
Classifier: Programming Language :: Python :: 3.9
Classifier: Programming Language :: Python :: 3.10
Classifier: Programming Language :: Python :: 3 :: Only
Requires-Python: >=3.6
License-File: LICENSE.rst
